data_schema/__init__.py
data_schema/apps.py
data_schema/convert_value.py
data_schema/exceptions.py
data_schema/field_schema_type.py
data_schema/models.py
data_schema/version.py
data_schema/migrations/0001_initial.py
data_schema/migrations/0002_auto_20150705_1714.py
data_schema/migrations/0003_auto_20151013_1556.py
data_schema/migrations/0004_fieldschema_case.py
data_schema/migrations/0005_auto_20180302_2356.py
data_schema/migrations/0006_auto_20220818_1425.py
data_schema/migrations/0007_auto_20230418_2042.py
data_schema/migrations/__init__.py
data_schema/tests/__init__.py
data_schema/tests/convert_value_tests.py
data_schema/tests/model_tests.py
data_schema/tests/tests.py
django_data_schema-2.1.0.dist-info/LICENSE
django_data_schema-2.1.0.dist-info/METADATA
django_data_schema-2.1.0.dist-info/WHEEL
django_data_schema-2.1.0.dist-info/top_level.txt
django_data_schema-2.1.0.dist-info/RECORD
