Metadata-Version: 2.1
Name: django-data-schema
Version: 2.1.0
Summary: Schemas over dictionaries and models in Django
Home-page: https://github.com/ambitioninc/django-data-schema
Author: Wes Kendall
Author-email: opensource@ambition.com
License: MIT
Keywords: Django Data Schema
Classifier: Programming Language :: Python
Classifier: Programming Language :: Python :: 3.7
Classifier: Programming Language :: Python :: 3.8
Classifier: Programming Language :: Python :: 3.9
Classifier: Intended Audience :: Developers
Classifier: License :: OSI Approved :: BSD License
Classifier: Operating System :: OS Independent
Classifier: Framework :: Django
Classifier: Framework :: Django :: 3.2
Classifier: Framework :: Django :: 4.0
Classifier: Framework :: Django :: 4.1
Classifier: Framework :: Django :: 4.2
License-File: LICENSE
Requires-Dist: Django (>=3.2)
Requires-Dist: django-manager-utils (>=3.1.0)
Requires-Dist: fleming (>=0.7.0)
Requires-Dist: python-dateutil (>=2.2)
